databricks_mcp/__init__.py
databricks_mcp/__main__.py
databricks_mcp/main.py
databricks_mcp/api/__init__.py
databricks_mcp/api/clusters.py
databricks_mcp/api/dbfs.py
databricks_mcp/api/genie.py
databricks_mcp/api/jobs.py
databricks_mcp/api/libraries.py
databricks_mcp/api/notebooks.py
databricks_mcp/api/repos.py
databricks_mcp/api/sql.py
databricks_mcp/api/unity_catalog.py
databricks_mcp/api/unity_catalog_enhanced.py
databricks_mcp/cli/__init__.py
databricks_mcp/cli/commands.py
databricks_mcp/core/__init__.py
databricks_mcp/core/auth.py
databricks_mcp/core/config.py
databricks_mcp/core/formatting.py
databricks_mcp/core/models.py
databricks_mcp/core/sql_safety.py
databricks_mcp/core/utils.py
databricks_mcp/server/__init__.py
databricks_mcp/server/__main__.py
databricks_mcp/server/app.py
databricks_mcp/server/databricks_mcp_server.py
databricks_mcp_genie-1.0.0.dist-info/METADATA
databricks_mcp_genie-1.0.0.dist-info/WHEEL
databricks_mcp_genie-1.0.0.dist-info/entry_points.txt
databricks_mcp_genie-1.0.0.dist-info/RECORD
